batched_melbo/__init__.py
batched_melbo/_modidx.py
batched_melbo/batched_melbo.py
batched_melbo/original_melbo.py
batched_melbo-0.1.1.dist-info/licenses/LICENSE
batched_melbo-0.1.1.dist-info/METADATA
batched_melbo-0.1.1.dist-info/WHEEL
batched_melbo-0.1.1.dist-info/entry_points.txt
batched_melbo-0.1.1.dist-info/top_level.txt
batched_melbo-0.1.1.dist-info/RECORD
