Metadata-Version: 2.4
Name: batched_melbo
Version: 0.1.1
Summary: Optimising unsupervised steering vector (a.k.a MELBO) training
Home-page: https://github.com/z3research/batched_melbo
Author: Mohammed Abu Baker, Dan Wilhelm
Author-email: muyabb@gmail.com, dan@danwil.com
License: Apache Software License 2.0
Keywords: nbdev jupyter notebook python
Classifier: Development Status :: 4 - Beta
Classifier: Intended Audience :: Developers
Classifier: Natural Language :: English
Classifier: Programming Language :: Python :: 3.11
Classifier: Programming Language :: Python :: 3.12
Classifier: License :: OSI Approved :: Apache Software License
Requires-Python: >=3.11
License-File: LICENSE
Requires-Dist: transformers>=4.39.2
Requires-Dist: torch>=2.2.1
Requires-Dist: tqdm>=4.65.0
Requires-Dist: jaxtyping>=0.3.3
Requires-Dist: ipykernel>=7.1.0
Requires-Dist: tiktoken>=0.12.0
Requires-Dist: einops>=0.8.1
Requires-Dist: accelerate>=1.12.0
Requires-Dist: matplotlib>=3.10.7
Requires-Dist: transformers-stream-generator>=0.0.5
Provides-Extra: dev
Dynamic: author
Dynamic: author-email
Dynamic: classifier
Dynamic: description
Dynamic: description-content-type
Dynamic: home-page
Dynamic: keywords
Dynamic: license
Dynamic: license-file
Dynamic: provides-extra
Dynamic: requires-python
